sonnixgres/__init__.py
sonnixgres/core.py
sonnixgres/exceptions.py
sonnixgres/logging_config.py
sonnixgres/utils.py
sonnixgres/validation.py
sonnixgres-0.2.0.dist-info/METADATA
sonnixgres-0.2.0.dist-info/WHEEL
sonnixgres-0.2.0.dist-info/licenses/LICENSE
sonnixgres-0.2.0.dist-info/RECORD
