Metadata-Version: 2.4
Name: sonnixgres
Version: 0.2.0
Summary: A production-ready Python library for PostgreSQL database interactions with connection pooling, query caching, and rich console output.
License: BSD-3-Clause
License-File: LICENSE
Keywords: postgresql,database,pandas,rich,cli
Author: Sonny Mir
Author-email: sonnym@hotmail.se
Classifier: Development Status :: 3 - Alpha
Classifier: Intended Audience :: Developers
Classifier: License :: OSI Approved :: BSD License
Classifier: Operating System :: OS Independent
Classifier: Programming Language :: Python :: 2
Classifier: Programming Language :: Python :: 2.7
Classifier: Programming Language :: Python :: 3
Classifier: Programming Language :: Python :: 3.4
Classifier: Programming Language :: Python :: 3.5
Classifier: Programming Language :: Python :: 3.6
Classifier: Programming Language :: Python :: 3.7
Classifier: Programming Language :: Python :: 3.8
Classifier: Programming Language :: Python :: 3.9
Classifier: Programming Language :: Python :: 3.10
Classifier: Programming Language :: Python :: 3.11
Classifier: Programming Language :: Python :: 3.12
Classifier: Programming Language :: Python :: 3.13
Classifier: Programming Language :: Python :: 3.14
Classifier: Topic :: Database
Classifier: Topic :: Utilities
Project-URL: Documentation, https://github.com/SuperSonnix71/sonnixgres#readme
Project-URL: Homepage, https://github.com/SuperSonnix71/sonnixgres
Project-URL: Repository, https://github.com/SuperSonnix71/sonnixgres
